{
  "good":     "✅",
  "warning":  "☢️",
  "bad":      "❌",
  "check":    "✅",
  "nocheck":  "❌",
  "fail":     "❌",
  "yes":      "✅",
  "no":       "❌",
  "delete":   "🚮",
  "reload":   "♻️",
  "wait":     "⏳",
  "skip":     "⏩",
  "prodText": "🎨",
  "devText":  "⚙️",
  "success":  "⭐",
  "current":  "=",
  "add":      "🔺",
  "remove":   "🔻",

  "prod":     "🌎",
  "dev":      "⚙️",
  "alert":    "⚠️",
  "up":       "🔼",
  "down":     "🔽",
  "stop":     "⏹️",
  "lock":     "🔒",
  "unlock":   "🔓",
  "bot":      "🤖",
  "user":     "👤",
  "null":     " ",

  "discord":  "💾🔌",
  "stoat":    "🔋🔋",
  "fluxer":   "☣️ ☣️"
}
